[{"Name":"Human","Confidence":99.28923034667969},{"Name":"People","Confidence":99.29280853271484},{"Name":"Person","Confidence":99.29280853271484},{"Name":"Face","Confidence":68.75370788574219},{"Name":"Selfie","Confidence":68.75370788574219},{"Name":"Fence","Confidence":63.45426559448242},{"Name":"Wall","Confidence":63.45426559448242},{"Name":"Man","Confidence":52.518409729003906},{"Name":"Portrait","Confidence":51.95635986328125},{"Name":"Brick","Confidence":51.07387924194336},{"Name":"Soil","Confidence":50.72489547729492}]